bsdspy/__init__.py
bsdspy/bsds.py
bsdspy-0.1.6.dist-info/METADATA
bsdspy-0.1.6.dist-info/WHEEL
bsdspy-0.1.6.dist-info/top_level.txt
bsdspy-0.1.6.dist-info/RECORD
